PL/__init__.py
PL/main.py
PL/Layout/__init__.py
PL/Layout/frames_buttons.py
PL/Layout/layouts_style.py
PL/Layout/main_window_att.py
PL/Layout/setting_windows.py
PL/Plot/__init__.py
PL/Plot/frame_attributes.py
PL/Plot/plot_functions.py
PL/Plot/plot_style.py
PL/Plot/utils.py
PL/Processing/__init__.py
PL/Processing/background.py
PL/Processing/function_common.py
PL/Processing/photoluminescence.py
PL/Processing/sequences.py
pl2d-1.0.3.dist-info/licenses/LICENSE
pl2d-1.0.3.dist-info/METADATA
pl2d-1.0.3.dist-info/WHEEL
pl2d-1.0.3.dist-info/entry_points.txt
pl2d-1.0.3.dist-info/top_level.txt
pl2d-1.0.3.dist-info/RECORD
