Metadata-Version: 2.4
Name: PL2D
Version: 1.0.3
Summary: Package for PL visualization
Author-email: Thibaut Meyer <thibaut.meyer3@gmail.com>
License-Expression: GPL-3.0-or-later
Project-URL: Homepage, https://github.com/thi-mey/PL2D
Keywords: PL,MoS2,2D
Classifier: Programming Language :: Python :: 3
Classifier: Operating System :: OS Independent
Requires-Python: >=3.9
License-File: LICENSE
Requires-Dist: matplotlib==3.10.3
Requires-Dist: numpy==2.2.5
Requires-Dist: pandas==2.2.3
Requires-Dist: Pillow==11.2.1
Requires-Dist: PyQt5==5.15.11
Requires-Dist: PyQt5_sip==12.17.0
Dynamic: license-file
